testpkg5_ftcao/__init__.py
testpkg5_ftcao/testpkg5_ftcao.py
testpkg5_ftcao-0.1.0.dist-info/LICENSE
testpkg5_ftcao-0.1.0.dist-info/METADATA
testpkg5_ftcao-0.1.0.dist-info/WHEEL
testpkg5_ftcao-0.1.0.dist-info/RECORD
